nose2pytest/__init__.py
nose2pytest/assert_tools.py
nose2pytest/script.py
nose2pytest-1.0.12.dist-info/LICENSE.txt
nose2pytest-1.0.12.dist-info/METADATA
nose2pytest-1.0.12.dist-info/WHEEL
nose2pytest-1.0.12.dist-info/entry_points.txt
nose2pytest-1.0.12.dist-info/top_level.txt
nose2pytest-1.0.12.dist-info/RECORD
