Metadata-Version: 2.1
Name: nose2pytest
Version: 1.0.12
Summary: Convert nose.tools.assert_ calls found in your Nose test modules into raw asserts for pytest
Home-page: https://github.com/schollii/nose2pytest
Author: Oliver Schoenborn
Author-email: oliver.schoenborn@gmail.com
License: BSD-3
Keywords: nose to pytest conversion
Classifier: Development Status :: 5 - Production/Stable
Classifier: Intended Audience :: Developers
Classifier: Topic :: Software Development :: Testing
Classifier: License :: OSI Approved :: BSD License
Classifier: Programming Language :: Python :: 3.6
Classifier: Programming Language :: Python :: 3.7
Classifier: Programming Language :: Python :: 3.8
Classifier: Programming Language :: Python :: 3.9
Classifier: Programming Language :: Python :: 3.10
Classifier: Programming Language :: Python :: 3.11
Requires-Python: >=3.6
License-File: LICENSE.txt
Requires-Dist: fissix
